calcrule_social_protection/__init__.py
calcrule_social_protection/admin.py
calcrule_social_protection/apps.py
calcrule_social_protection/calculation_rule.py
calcrule_social_protection/config.py
calcrule_social_protection/models.py
calcrule_social_protection/signals.py
calcrule_social_protection/tests.py
calcrule_social_protection/urls.py
calcrule_social_protection/utils.py
calcrule_social_protection/views.py
calcrule_social_protection/converters/__init__.py
calcrule_social_protection/converters/beneficiary/__init__.py
calcrule_social_protection/converters/beneficiary/beneficiary_to_benefit.py
calcrule_social_protection/converters/beneficiary/beneficiary_to_bill.py
calcrule_social_protection/converters/beneficiary/beneficiary_to_bill_item.py
calcrule_social_protection/converters/builder/__init__.py
calcrule_social_protection/converters/builder/builder_to_benefit.py
calcrule_social_protection/converters/builder/builder_to_bill.py
calcrule_social_protection/converters/builder/builder_to_bill_item.py
calcrule_social_protection/converters/group_beneficiary/__init__.py
calcrule_social_protection/converters/group_beneficiary/group_to_benefit.py
calcrule_social_protection/converters/group_beneficiary/group_to_bill.py
calcrule_social_protection/converters/group_beneficiary/group_to_bill_item.py
calcrule_social_protection/migrations/__init__.py
calcrule_social_protection/strategies/__init__.py
calcrule_social_protection/strategies/benefit_package_base_strategy.py
calcrule_social_protection/strategies/benefit_package_group_strategy.py
calcrule_social_protection/strategies/benefit_package_individual_strategy.py
calcrule_social_protection/strategies/benefit_package_strategy_interface.py
calcrule_social_protection/strategies/benefit_package_strategy_storage.py
openimis_be_calcrule_social_protection-1.2.0.dist-info/LICENSE.md
openimis_be_calcrule_social_protection-1.2.0.dist-info/METADATA
openimis_be_calcrule_social_protection-1.2.0.dist-info/WHEEL
openimis_be_calcrule_social_protection-1.2.0.dist-info/top_level.txt
openimis_be_calcrule_social_protection-1.2.0.dist-info/RECORD
