Metadata-Version: 2.1
Name: openimis-be-calcrule_social_protection
Version: 1.2.0
Summary: The openIMIS Backend calcrule_social_protection reference module.
Home-page: https://openimis.org/
Author: sniedzielski
Author-email: sniedzielski@soldevelo.com
License: GNU AGPL v3
Classifier: Environment :: Web Environment
Classifier: Framework :: Django
Classifier: Framework :: Django :: 3.0
Classifier: Intended Audience :: Developers
Classifier: License :: OSI Approved :: GNU Affero General Public License v3
Classifier: Operating System :: OS Independent
Classifier: Programming Language :: Python
Classifier: Programming Language :: Python :: 3.8
License-File: LICENSE.md
Requires-Dist: django
Requires-Dist: django-db-signals
Requires-Dist: djangorestframework
Requires-Dist: openimis-be-core
Requires-Dist: openimis-be-invoice
Requires-Dist: openimis-be-individual
Requires-Dist: openimis-be-social-protection
Requires-Dist: openimis-be-payroll
